{
  "game_id": "14aad394-7f03-48a0-8599-e12fa82e3480",
  "version": "2",
  "sona": "1",
  "experiment_id": "1768",
  "credit_token": "19421bc286424246b6b1e873e7a55a8e",
  "survey_code": "19944",
  "player1_id": "aaafd4bd-0d3f-402e-9cd7-7ee17c483089",
  "player2_id": "bot",
  "rounds": [
    {
      "game_id": "14aad394-7f03-48a0-8599-e12fa82e3480",
      "version": "2",
      "round_index": 1,
      "player1_id": "aaafd4bd-0d3f-402e-9cd7-7ee17c483089",
      "player2_id": "bot",
      "round_begin_ts": 1583285520340,
      "player1_move": "scissors",
      "player2_move": "rock",
      "player1_rt": 2477,
      "player2_rt": 0,
      "player1_outcome": "loss",
      "player2_outcome": "win",
      "player1_outcome_viewtime": 3080,
      "player2_outcome_viewtime": 0,
      "player1_points": -1,
      "player2_points": 3,
      "player1_total": 0,
      "player2_total": 0
    },
    {
      "game_id": "14aad394-7f03-48a0-8599-e12fa82e3480",
      "version": "2",
      "round_index": 2,
      "player1_id": "aaafd4bd-0d3f-402e-9cd7-7ee17c483089",
      "player2_id": "bot",
      "round_begin_ts": 1583285525957,
      "player1_move": "paper",
      "player2_move": "paper",
      "player1_rt": 1063,
      "player2_rt": 0,
      "player1_outcome": "tie",
      "player2_outcome": "tie",
      "player1_outcome_viewtime": 1310,
      "player2_outcome_viewtime": 0,
      "player1_points": 0,
      "player2_points": 0,
      "player1_total": -1,
      "player2_total": 3
    },
    {
      "game_id": "14aad394-7f03-48a0-8599-e12fa82e3480",
      "version": "2",
      "round_index": 3,
      "player1_id": "aaafd4bd-0d3f-402e-9cd7-7ee17c483089",
      "player2_id": "bot",
      "round_begin_ts": 1583285528363,
      "player1_move": "rock",
      "player2_move": "paper",
      "player1_rt": 590,
      "player2_rt": 0,
      "player1_outcome": "loss",
      "player2_outcome": "win",
      "player1_outcome_viewtime": 1015,
      "player2_outcome_viewtime": 0,
      "player1_points": -1,
      "player2_points": 3,
      "player1_total": -1,
      "player2_total": 3
    },
    {
      "game_id": "14aad394-7f03-48a0-8599-e12fa82e3480",
      "version": "2",
      "round_index": 4,
      "player1_id": "aaafd4bd-0d3f-402e-9cd7-7ee17c483089",
      "player2_id": "bot",
      "round_begin_ts": 1583285529996,
      "player1_move": "paper",
      "player2_move": "paper",
      "player1_rt": 1043,
      "player2_rt": 0,
      "player1_outcome": "tie",
      "player2_outcome": "tie",
      "player1_outcome_viewtime": 2029,
      "player2_outcome_viewtime": 0,
      "player1_points": 0,
      "player2_points": 0,
      "player1_total": -2,
      "player2_total": 6
    },
    {
      "game_id": "14aad394-7f03-48a0-8599-e12fa82e3480",
      "version": "2",
      "round_index": 5,
      "player1_id": "aaafd4bd-0d3f-402e-9cd7-7ee17c483089",
      "player2_id": "bot",
      "round_begin_ts": 1583285533109,
      "player1_move": "scissors",
      "player2_move": "paper",
      "player1_rt": 909,
      "player2_rt": 0,
      "player1_outcome": "win",
      "player2_outcome": "loss",
      "player1_outcome_viewtime": 4333,
      "player2_outcome_viewtime": 0,
      "player1_points": 3,
      "player2_points": -1,
      "player1_total": -2,
      "player2_total": 6
    },
    {
      "game_id": "14aad394-7f03-48a0-8599-e12fa82e3480",
      "version": "2",
      "round_index": 6,
      "player1_id": "aaafd4bd-0d3f-402e-9cd7-7ee17c483089",
      "player2_id": "bot",
      "round_begin_ts": 1583285538383,
      "player1_move": "paper",
      "player2_move": "rock",
      "player1_rt": 827,
      "player2_rt": 0,
      "player1_outcome": "win",
      "player2_outcome": "loss",
      "player1_outcome_viewtime": 1334,
      "player2_outcome_viewtime": 0,
      "player1_points": 3,
      "player2_points": -1,
      "player1_total": 1,
      "player2_total": 5
    },
    {
      "game_id": "14aad394-7f03-48a0-8599-e12fa82e3480",
      "version": "2",
      "round_index": 7,
      "player1_id": "aaafd4bd-0d3f-402e-9cd7-7ee17c483089",
      "player2_id": "bot",
      "round_begin_ts": 1583285540576,
      "player1_move": "rock",
      "player2_move": "scissors",
      "player1_rt": 736,
      "player2_rt": 0,
      "player1_outcome": "win",
      "player2_outcome": "loss",
      "player1_outcome_viewtime": 1149,
      "player2_outcome_viewtime": 0,
      "player1_points": 3,
      "player2_points": -1,
      "player1_total": 4,
      "player2_total": 4
    },
    {
      "game_id": "14aad394-7f03-48a0-8599-e12fa82e3480",
      "version": "2",
      "round_index": 8,
      "player1_id": "aaafd4bd-0d3f-402e-9cd7-7ee17c483089",
      "player2_id": "bot",
      "round_begin_ts": 1583285542492,
      "player1_move": "scissors",
      "player2_move": "paper",
      "player1_rt": 787,
      "player2_rt": 0,
      "player1_outcome": "win",
      "player2_outcome": "loss",
      "player1_outcome_viewtime": 906,
      "player2_outcome_viewtime": 0,
      "player1_points": 3,
      "player2_points": -1,
      "player1_total": 7,
      "player2_total": 3
    },
    {
      "game_id": "14aad394-7f03-48a0-8599-e12fa82e3480",
      "version": "2",
      "round_index": 9,
      "player1_id": "aaafd4bd-0d3f-402e-9cd7-7ee17c483089",
      "player2_id": "bot",
      "round_begin_ts": 1583285544215,
      "player1_move": "paper",
      "player2_move": "rock",
      "player1_rt": 939,
      "player2_rt": 0,
      "player1_outcome": "win",
      "player2_outcome": "loss",
      "player1_outcome_viewtime": 1017,
      "player2_outcome_viewtime": 0,
      "player1_points": 3,
      "player2_points": -1,
      "player1_total": 10,
      "player2_total": 2
    },
    {
      "game_id": "14aad394-7f03-48a0-8599-e12fa82e3480",
      "version": "2",
      "round_index": 10,
      "player1_id": "aaafd4bd-0d3f-402e-9cd7-7ee17c483089",
      "player2_id": "bot",
      "round_begin_ts": 1583285546202,
      "player1_move": "rock",
      "player2_move": "rock",
      "player1_rt": 1255,
      "player2_rt": 0,
      "player1_outcome": "tie",
      "player2_outcome": "tie",
      "player1_outcome_viewtime": 913,
      "player2_outcome_viewtime": 0,
      "player1_points": 0,
      "player2_points": 0,
      "player1_total": 13,
      "player2_total": 1
    },
    {
      "game_id": "14aad394-7f03-48a0-8599-e12fa82e3480",
      "version": "2",
      "round_index": 11,
      "player1_id": "aaafd4bd-0d3f-402e-9cd7-7ee17c483089",
      "player2_id": "bot",
      "round_begin_ts": 1583285548400,
      "player1_move": "scissors",
      "player2_move": "rock",
      "player1_rt": 1687,
      "player2_rt": 0,
      "player1_outcome": "loss",
      "player2_outcome": "win",
      "player1_outcome_viewtime": 914,
      "player2_outcome_viewtime": 0,
      "player1_points": -1,
      "player2_points": 3,
      "player1_total": 13,
      "player2_total": 1
    },
    {
      "game_id": "14aad394-7f03-48a0-8599-e12fa82e3480",
      "version": "2",
      "round_index": 12,
      "player1_id": "aaafd4bd-0d3f-402e-9cd7-7ee17c483089",
      "player2_id": "bot",
      "round_begin_ts": 1583285551029,
      "player1_move": "paper",
      "player2_move": "paper",
      "player1_rt": 1263,
      "player2_rt": 0,
      "player1_outcome": "tie",
      "player2_outcome": "tie",
      "player1_outcome_viewtime": 1245,
      "player2_outcome_viewtime": 0,
      "player1_points": 0,
      "player2_points": 0,
      "player1_total": 12,
      "player2_total": 4
    },
    {
      "game_id": "14aad394-7f03-48a0-8599-e12fa82e3480",
      "version": "2",
      "round_index": 13,
      "player1_id": "aaafd4bd-0d3f-402e-9cd7-7ee17c483089",
      "player2_id": "bot",
      "round_begin_ts": 1583285553563,
      "player1_move": "scissors",
      "player2_move": "paper",
      "player1_rt": 971,
      "player2_rt": 0,
      "player1_outcome": "win",
      "player2_outcome": "loss",
      "player1_outcome_viewtime": 1038,
      "player2_outcome_viewtime": 0,
      "player1_points": 3,
      "player2_points": -1,
      "player1_total": 12,
      "player2_total": 4
    },
    {
      "game_id": "14aad394-7f03-48a0-8599-e12fa82e3480",
      "version": "2",
      "round_index": 14,
      "player1_id": "aaafd4bd-0d3f-402e-9cd7-7ee17c483089",
      "player2_id": "bot",
      "round_begin_ts": 1583285555602,
      "player1_move": "scissors",
      "player2_move": "rock",
      "player1_rt": 1050,
      "player2_rt": 0,
      "player1_outcome": "loss",
      "player2_outcome": "win",
      "player1_outcome_viewtime": 1268,
      "player2_outcome_viewtime": 0,
      "player1_points": -1,
      "player2_points": 3,
      "player1_total": 15,
      "player2_total": 3
    },
    {
      "game_id": "14aad394-7f03-48a0-8599-e12fa82e3480",
      "version": "2",
      "round_index": 15,
      "player1_id": "aaafd4bd-0d3f-402e-9cd7-7ee17c483089",
      "player2_id": "bot",
      "round_begin_ts": 1583285557950,
      "player1_move": "scissors",
      "player2_move": "scissors",
      "player1_rt": 1000,
      "player2_rt": 0,
      "player1_outcome": "tie",
      "player2_outcome": "tie",
      "player1_outcome_viewtime": 872,
      "player2_outcome_viewtime": 0,
      "player1_points": 0,
      "player2_points": 0,
      "player1_total": 14,
      "player2_total": 6
    },
    {
      "game_id": "14aad394-7f03-48a0-8599-e12fa82e3480",
      "version": "2",
      "round_index": 16,
      "player1_id": "aaafd4bd-0d3f-402e-9cd7-7ee17c483089",
      "player2_id": "bot",
      "round_begin_ts": 1583285559851,
      "player1_move": "scissors",
      "player2_move": "scissors",
      "player1_rt": 770,
      "player2_rt": 0,
      "player1_outcome": "tie",
      "player2_outcome": "tie",
      "player1_outcome_viewtime": 852,
      "player2_outcome_viewtime": 0,
      "player1_points": 0,
      "player2_points": 0,
      "player1_total": 14,
      "player2_total": 6
    },
    {
      "game_id": "14aad394-7f03-48a0-8599-e12fa82e3480",
      "version": "2",
      "round_index": 17,
      "player1_id": "aaafd4bd-0d3f-402e-9cd7-7ee17c483089",
      "player2_id": "bot",
      "round_begin_ts": 1583285561507,
      "player1_move": "scissors",
      "player2_move": "scissors",
      "player1_rt": 655,
      "player2_rt": 0,
      "player1_outcome": "tie",
      "player2_outcome": "tie",
      "player1_outcome_viewtime": 998,
      "player2_outcome_viewtime": 0,
      "player1_points": 0,
      "player2_points": 0,
      "player1_total": 14,
      "player2_total": 6
    },
    {
      "game_id": "14aad394-7f03-48a0-8599-e12fa82e3480",
      "version": "2",
      "round_index": 18,
      "player1_id": "aaafd4bd-0d3f-402e-9cd7-7ee17c483089",
      "player2_id": "bot",
      "round_begin_ts": 1583285563188,
      "player1_move": "scissors",
      "player2_move": "scissors",
      "player1_rt": 816,
      "player2_rt": 0,
      "player1_outcome": "tie",
      "player2_outcome": "tie",
      "player1_outcome_viewtime": 818,
      "player2_outcome_viewtime": 0,
      "player1_points": 0,
      "player2_points": 0,
      "player1_total": 14,
      "player2_total": 6
    },
    {
      "game_id": "14aad394-7f03-48a0-8599-e12fa82e3480",
      "version": "2",
      "round_index": 19,
      "player1_id": "aaafd4bd-0d3f-402e-9cd7-7ee17c483089",
      "player2_id": "bot",
      "round_begin_ts": 1583285564854,
      "player1_move": "scissors",
      "player2_move": "scissors",
      "player1_rt": 669,
      "player2_rt": 0,
      "player1_outcome": "tie",
      "player2_outcome": "tie",
      "player1_outcome_viewtime": 1068,
      "player2_outcome_viewtime": 0,
      "player1_points": 0,
      "player2_points": 0,
      "player1_total": 14,
      "player2_total": 6
    },
    {
      "game_id": "14aad394-7f03-48a0-8599-e12fa82e3480",
      "version": "2",
      "round_index": 20,
      "player1_id": "aaafd4bd-0d3f-402e-9cd7-7ee17c483089",
      "player2_id": "bot",
      "round_begin_ts": 1583285566621,
      "player1_move": "scissors",
      "player2_move": "paper",
      "player1_rt": 547,
      "player2_rt": 0,
      "player1_outcome": "win",
      "player2_outcome": "loss",
      "player1_outcome_viewtime": 1210,
      "player2_outcome_viewtime": 0,
      "player1_points": 3,
      "player2_points": -1,
      "player1_total": 14,
      "player2_total": 6
    },
    {
      "game_id": "14aad394-7f03-48a0-8599-e12fa82e3480",
      "version": "2",
      "round_index": 21,
      "player1_id": "aaafd4bd-0d3f-402e-9cd7-7ee17c483089",
      "player2_id": "bot",
      "round_begin_ts": 1583285568407,
      "player1_move": "paper",
      "player2_move": "rock",
      "player1_rt": 2703,
      "player2_rt": 0,
      "player1_outcome": "win",
      "player2_outcome": "loss",
      "player1_outcome_viewtime": 850,
      "player2_outcome_viewtime": 0,
      "player1_points": 3,
      "player2_points": -1,
      "player1_total": 17,
      "player2_total": 5
    },
    {
      "game_id": "14aad394-7f03-48a0-8599-e12fa82e3480",
      "version": "2",
      "round_index": 22,
      "player1_id": "aaafd4bd-0d3f-402e-9cd7-7ee17c483089",
      "player2_id": "bot",
      "round_begin_ts": 1583285571991,
      "player1_move": "scissors",
      "player2_move": "scissors",
      "player1_rt": 1104,
      "player2_rt": 0,
      "player1_outcome": "tie",
      "player2_outcome": "tie",
      "player1_outcome_viewtime": 1029,
      "player2_outcome_viewtime": 0,
      "player1_points": 0,
      "player2_points": 0,
      "player1_total": 20,
      "player2_total": 4
    },
    {
      "game_id": "14aad394-7f03-48a0-8599-e12fa82e3480",
      "version": "2",
      "round_index": 23,
      "player1_id": "aaafd4bd-0d3f-402e-9cd7-7ee17c483089",
      "player2_id": "bot",
      "round_begin_ts": 1583285574152,
      "player1_move": "rock",
      "player2_move": "scissors",
      "player1_rt": 786,
      "player2_rt": 0,
      "player1_outcome": "win",
      "player2_outcome": "loss",
      "player1_outcome_viewtime": 875,
      "player2_outcome_viewtime": 0,
      "player1_points": 3,
      "player2_points": -1,
      "player1_total": 20,
      "player2_total": 4
    },
    {
      "game_id": "14aad394-7f03-48a0-8599-e12fa82e3480",
      "version": "2",
      "round_index": 24,
      "player1_id": "aaafd4bd-0d3f-402e-9cd7-7ee17c483089",
      "player2_id": "bot",
      "round_begin_ts": 1583285575839,
      "player1_move": "rock",
      "player2_move": "paper",
      "player1_rt": 734,
      "player2_rt": 0,
      "player1_outcome": "loss",
      "player2_outcome": "win",
      "player1_outcome_viewtime": 1321,
      "player2_outcome_viewtime": 0,
      "player1_points": -1,
      "player2_points": 3,
      "player1_total": 23,
      "player2_total": 3
    },
    {
      "game_id": "14aad394-7f03-48a0-8599-e12fa82e3480",
      "version": "2",
      "round_index": 25,
      "player1_id": "aaafd4bd-0d3f-402e-9cd7-7ee17c483089",
      "player2_id": "bot",
      "round_begin_ts": 1583285577919,
      "player1_move": "scissors",
      "player2_move": "scissors",
      "player1_rt": 1369,
      "player2_rt": 0,
      "player1_outcome": "tie",
      "player2_outcome": "tie",
      "player1_outcome_viewtime": 732,
      "player2_outcome_viewtime": 0,
      "player1_points": 0,
      "player2_points": 0,
      "player1_total": 22,
      "player2_total": 6
    },
    {
      "game_id": "14aad394-7f03-48a0-8599-e12fa82e3480",
      "version": "2",
      "round_index": 26,
      "player1_id": "aaafd4bd-0d3f-402e-9cd7-7ee17c483089",
      "player2_id": "bot",
      "round_begin_ts": 1583285580049,
      "player1_move": "paper",
      "player2_move": "paper",
      "player1_rt": 568,
      "player2_rt": 0,
      "player1_outcome": "tie",
      "player2_outcome": "tie",
      "player1_outcome_viewtime": 762,
      "player2_outcome_viewtime": 0,
      "player1_points": 0,
      "player2_points": 0,
      "player1_total": 22,
      "player2_total": 6
    },
    {
      "game_id": "14aad394-7f03-48a0-8599-e12fa82e3480",
      "version": "2",
      "round_index": 27,
      "player1_id": "aaafd4bd-0d3f-402e-9cd7-7ee17c483089",
      "player2_id": "bot",
      "round_begin_ts": 1583285581412,
      "player1_move": "scissors",
      "player2_move": "paper",
      "player1_rt": 665,
      "player2_rt": 0,
      "player1_outcome": "win",
      "player2_outcome": "loss",
      "player1_outcome_viewtime": 660,
      "player2_outcome_viewtime": 0,
      "player1_points": 3,
      "player2_points": -1,
      "player1_total": 22,
      "player2_total": 6
    },
    {
      "game_id": "14aad394-7f03-48a0-8599-e12fa82e3480",
      "version": "2",
      "round_index": 28,
      "player1_id": "aaafd4bd-0d3f-402e-9cd7-7ee17c483089",
      "player2_id": "bot",
      "round_begin_ts": 1583285582767,
      "player1_move": "paper",
      "player2_move": "rock",
      "player1_rt": 573,
      "player2_rt": 0,
      "player1_outcome": "win",
      "player2_outcome": "loss",
      "player1_outcome_viewtime": 657,
      "player2_outcome_viewtime": 0,
      "player1_points": 3,
      "player2_points": -1,
      "player1_total": 25,
      "player2_total": 5
    },
    {
      "game_id": "14aad394-7f03-48a0-8599-e12fa82e3480",
      "version": "2",
      "round_index": 29,
      "player1_id": "aaafd4bd-0d3f-402e-9cd7-7ee17c483089",
      "player2_id": "bot",
      "round_begin_ts": 1583285584021,
      "player1_move": "rock",
      "player2_move": "scissors",
      "player1_rt": 605,
      "player2_rt": 0,
      "player1_outcome": "win",
      "player2_outcome": "loss",
      "player1_outcome_viewtime": 751,
      "player2_outcome_viewtime": 0,
      "player1_points": 3,
      "player2_points": -1,
      "player1_total": 28,
      "player2_total": 4
    },
    {
      "game_id": "14aad394-7f03-48a0-8599-e12fa82e3480",
      "version": "2",
      "round_index": 30,
      "player1_id": "aaafd4bd-0d3f-402e-9cd7-7ee17c483089",
      "player2_id": "bot",
      "round_begin_ts": 1583285585404,
      "player1_move": "scissors",
      "player2_move": "scissors",
      "player1_rt": 485,
      "player2_rt": 0,
      "player1_outcome": "tie",
      "player2_outcome": "tie",
      "player1_outcome_viewtime": 552,
      "player2_outcome_viewtime": 0,
      "player1_points": 0,
      "player2_points": 0,
      "player1_total": 31,
      "player2_total": 3
    },
    {
      "game_id": "14aad394-7f03-48a0-8599-e12fa82e3480",
      "version": "2",
      "round_index": 31,
      "player1_id": "aaafd4bd-0d3f-402e-9cd7-7ee17c483089",
      "player2_id": "bot",
      "round_begin_ts": 1583285586470,
      "player1_move": "paper",
      "player2_move": "scissors",
      "player1_rt": 663,
      "player2_rt": 0,
      "player1_outcome": "loss",
      "player2_outcome": "win",
      "player1_outcome_viewtime": 575,
      "player2_outcome_viewtime": 0,
      "player1_points": -1,
      "player2_points": 3,
      "player1_total": 31,
      "player2_total": 3
    },
    {
      "game_id": "14aad394-7f03-48a0-8599-e12fa82e3480",
      "version": "2",
      "round_index": 32,
      "player1_id": "aaafd4bd-0d3f-402e-9cd7-7ee17c483089",
      "player2_id": "bot",
      "round_begin_ts": 1583285587739,
      "player1_move": "paper",
      "player2_move": "rock",
      "player1_rt": 477,
      "player2_rt": 0,
      "player1_outcome": "win",
      "player2_outcome": "loss",
      "player1_outcome_viewtime": 894,
      "player2_outcome_viewtime": 0,
      "player1_points": 3,
      "player2_points": -1,
      "player1_total": 30,
      "player2_total": 6
    },
    {
      "game_id": "14aad394-7f03-48a0-8599-e12fa82e3480",
      "version": "2",
      "round_index": 33,
      "player1_id": "aaafd4bd-0d3f-402e-9cd7-7ee17c483089",
      "player2_id": "bot",
      "round_begin_ts": 1583285589136,
      "player1_move": "paper",
      "player2_move": "scissors",
      "player1_rt": 559,
      "player2_rt": 0,
      "player1_outcome": "loss",
      "player2_outcome": "win",
      "player1_outcome_viewtime": 707,
      "player2_outcome_viewtime": 0,
      "player1_points": -1,
      "player2_points": 3,
      "player1_total": 33,
      "player2_total": 5
    },
    {
      "game_id": "14aad394-7f03-48a0-8599-e12fa82e3480",
      "version": "2",
      "round_index": 34,
      "player1_id": "aaafd4bd-0d3f-402e-9cd7-7ee17c483089",
      "player2_id": "bot",
      "round_begin_ts": 1583285590437,
      "player1_move": "paper",
      "player2_move": "rock",
      "player1_rt": 813,
      "player2_rt": 0,
      "player1_outcome": "win",
      "player2_outcome": "loss",
      "player1_outcome_viewtime": 834,
      "player2_outcome_viewtime": 0,
      "player1_points": 3,
      "player2_points": -1,
      "player1_total": 32,
      "player2_total": 8
    },
    {
      "game_id": "14aad394-7f03-48a0-8599-e12fa82e3480",
      "version": "2",
      "round_index": 35,
      "player1_id": "aaafd4bd-0d3f-402e-9cd7-7ee17c483089",
      "player2_id": "bot",
      "round_begin_ts": 1583285592114,
      "player1_move": "paper",
      "player2_move": "scissors",
      "player1_rt": 1096,
      "player2_rt": 0,
      "player1_outcome": "loss",
      "player2_outcome": "win",
      "player1_outcome_viewtime": 970,
      "player2_outcome_viewtime": 0,
      "player1_points": -1,
      "player2_points": 3,
      "player1_total": 35,
      "player2_total": 7
    },
    {
      "game_id": "14aad394-7f03-48a0-8599-e12fa82e3480",
      "version": "2",
      "round_index": 36,
      "player1_id": "aaafd4bd-0d3f-402e-9cd7-7ee17c483089",
      "player2_id": "bot",
      "round_begin_ts": 1583285594214,
      "player1_move": "paper",
      "player2_move": "rock",
      "player1_rt": 893,
      "player2_rt": 0,
      "player1_outcome": "win",
      "player2_outcome": "loss",
      "player1_outcome_viewtime": 755,
      "player2_outcome_viewtime": 0,
      "player1_points": 3,
      "player2_points": -1,
      "player1_total": 34,
      "player2_total": 10
    },
    {
      "game_id": "14aad394-7f03-48a0-8599-e12fa82e3480",
      "version": "2",
      "round_index": 37,
      "player1_id": "aaafd4bd-0d3f-402e-9cd7-7ee17c483089",
      "player2_id": "bot",
      "round_begin_ts": 1583285595891,
      "player1_move": "scissors",
      "player2_move": "rock",
      "player1_rt": 746,
      "player2_rt": 0,
      "player1_outcome": "loss",
      "player2_outcome": "win",
      "player1_outcome_viewtime": 712,
      "player2_outcome_viewtime": 0,
      "player1_points": -1,
      "player2_points": 3,
      "player1_total": 37,
      "player2_total": 9
    },
    {
      "game_id": "14aad394-7f03-48a0-8599-e12fa82e3480",
      "version": "2",
      "round_index": 38,
      "player1_id": "aaafd4bd-0d3f-402e-9cd7-7ee17c483089",
      "player2_id": "bot",
      "round_begin_ts": 1583285597379,
      "player1_move": "paper",
      "player2_move": "paper",
      "player1_rt": 540,
      "player2_rt": 0,
      "player1_outcome": "tie",
      "player2_outcome": "tie",
      "player1_outcome_viewtime": 1085,
      "player2_outcome_viewtime": 0,
      "player1_points": 0,
      "player2_points": 0,
      "player1_total": 36,
      "player2_total": 12
    },
    {
      "game_id": "14aad394-7f03-48a0-8599-e12fa82e3480",
      "version": "2",
      "round_index": 39,
      "player1_id": "aaafd4bd-0d3f-402e-9cd7-7ee17c483089",
      "player2_id": "bot",
      "round_begin_ts": 1583285599038,
      "player1_move": "scissors",
      "player2_move": "paper",
      "player1_rt": 842,
      "player2_rt": 0,
      "player1_outcome": "win",
      "player2_outcome": "loss",
      "player1_outcome_viewtime": 747,
      "player2_outcome_viewtime": 0,
      "player1_points": 3,
      "player2_points": -1,
      "player1_total": 36,
      "player2_total": 12
    },
    {
      "game_id": "14aad394-7f03-48a0-8599-e12fa82e3480",
      "version": "2",
      "round_index": 40,
      "player1_id": "aaafd4bd-0d3f-402e-9cd7-7ee17c483089",
      "player2_id": "bot",
      "round_begin_ts": 1583285600656,
      "player1_move": "scissors",
      "player2_move": "scissors",
      "player1_rt": 1161,
      "player2_rt": 0,
      "player1_outcome": "tie",
      "player2_outcome": "tie",
      "player1_outcome_viewtime": 706,
      "player2_outcome_viewtime": 0,
      "player1_points": 0,
      "player2_points": 0,
      "player1_total": 39,
      "player2_total": 11
    },
    {
      "game_id": "14aad394-7f03-48a0-8599-e12fa82e3480",
      "version": "2",
      "round_index": 41,
      "player1_id": "aaafd4bd-0d3f-402e-9cd7-7ee17c483089",
      "player2_id": "bot",
      "round_begin_ts": 1583285602554,
      "player1_move": "rock",
      "player2_move": "scissors",
      "player1_rt": 979,
      "player2_rt": 0,
      "player1_outcome": "win",
      "player2_outcome": "loss",
      "player1_outcome_viewtime": 800,
      "player2_outcome_viewtime": 0,
      "player1_points": 3,
      "player2_points": -1,
      "player1_total": 39,
      "player2_total": 11
    },
    {
      "game_id": "14aad394-7f03-48a0-8599-e12fa82e3480",
      "version": "2",
      "round_index": 42,
      "player1_id": "aaafd4bd-0d3f-402e-9cd7-7ee17c483089",
      "player2_id": "bot",
      "round_begin_ts": 1583285604362,
      "player1_move": "rock",
      "player2_move": "paper",
      "player1_rt": 751,
      "player2_rt": 0,
      "player1_outcome": "loss",
      "player2_outcome": "win",
      "player1_outcome_viewtime": 966,
      "player2_outcome_viewtime": 0,
      "player1_points": -1,
      "player2_points": 3,
      "player1_total": 42,
      "player2_total": 10
    },
    {
      "game_id": "14aad394-7f03-48a0-8599-e12fa82e3480",
      "version": "2",
      "round_index": 43,
      "player1_id": "aaafd4bd-0d3f-402e-9cd7-7ee17c483089",
      "player2_id": "bot",
      "round_begin_ts": 1583285606108,
      "player1_move": "scissors",
      "player2_move": "scissors",
      "player1_rt": 636,
      "player2_rt": 0,
      "player1_outcome": "tie",
      "player2_outcome": "tie",
      "player1_outcome_viewtime": 1036,
      "player2_outcome_viewtime": 0,
      "player1_points": 0,
      "player2_points": 0,
      "player1_total": 41,
      "player2_total": 13
    },
    {
      "game_id": "14aad394-7f03-48a0-8599-e12fa82e3480",
      "version": "2",
      "round_index": 44,
      "player1_id": "aaafd4bd-0d3f-402e-9cd7-7ee17c483089",
      "player2_id": "bot",
      "round_begin_ts": 1583285607813,
      "player1_move": "rock",
      "player2_move": "paper",
      "player1_rt": 562,
      "player2_rt": 0,
      "player1_outcome": "loss",
      "player2_outcome": "win",
      "player1_outcome_viewtime": 1606,
      "player2_outcome_viewtime": 0,
      "player1_points": -1,
      "player2_points": 3,
      "player1_total": 41,
      "player2_total": 13
    },
    {
      "game_id": "14aad394-7f03-48a0-8599-e12fa82e3480",
      "version": "2",
      "round_index": 45,
      "player1_id": "aaafd4bd-0d3f-402e-9cd7-7ee17c483089",
      "player2_id": "bot",
      "round_begin_ts": 1583285610034,
      "player1_move": "scissors",
      "player2_move": "paper",
      "player1_rt": 1022,
      "player2_rt": 0,
      "player1_outcome": "win",
      "player2_outcome": "loss",
      "player1_outcome_viewtime": 1465,
      "player2_outcome_viewtime": 0,
      "player1_points": 3,
      "player2_points": -1,
      "player1_total": 40,
      "player2_total": 16
    },
    {
      "game_id": "14aad394-7f03-48a0-8599-e12fa82e3480",
      "version": "2",
      "round_index": 46,
      "player1_id": "aaafd4bd-0d3f-402e-9cd7-7ee17c483089",
      "player2_id": "bot",
      "round_begin_ts": 1583285612558,
      "player1_move": "paper",
      "player2_move": "rock",
      "player1_rt": 1221,
      "player2_rt": 0,
      "player1_outcome": "win",
      "player2_outcome": "loss",
      "player1_outcome_viewtime": 1645,
      "player2_outcome_viewtime": 0,
      "player1_points": 3,
      "player2_points": -1,
      "player1_total": 43,
      "player2_total": 15
    },
    {
      "game_id": "14aad394-7f03-48a0-8599-e12fa82e3480",
      "version": "2",
      "round_index": 47,
      "player1_id": "aaafd4bd-0d3f-402e-9cd7-7ee17c483089",
      "player2_id": "bot",
      "round_begin_ts": 1583285615453,
      "player1_move": "scissors",
      "player2_move": "scissors",
      "player1_rt": 640,
      "player2_rt": 0,
      "player1_outcome": "tie",
      "player2_outcome": "tie",
      "player1_outcome_viewtime": 548,
      "player2_outcome_viewtime": 0,
      "player1_points": 0,
      "player2_points": 0,
      "player1_total": 46,
      "player2_total": 14
    },
    {
      "game_id": "14aad394-7f03-48a0-8599-e12fa82e3480",
      "version": "2",
      "round_index": 48,
      "player1_id": "aaafd4bd-0d3f-402e-9cd7-7ee17c483089",
      "player2_id": "bot",
      "round_begin_ts": 1583285616692,
      "player1_move": "paper",
      "player2_move": "scissors",
      "player1_rt": 606,
      "player2_rt": 0,
      "player1_outcome": "loss",
      "player2_outcome": "win",
      "player1_outcome_viewtime": 891,
      "player2_outcome_viewtime": 0,
      "player1_points": -1,
      "player2_points": 3,
      "player1_total": 46,
      "player2_total": 14
    },
    {
      "game_id": "14aad394-7f03-48a0-8599-e12fa82e3480",
      "version": "2",
      "round_index": 49,
      "player1_id": "aaafd4bd-0d3f-402e-9cd7-7ee17c483089",
      "player2_id": "bot",
      "round_begin_ts": 1583285618215,
      "player1_move": "scissors",
      "player2_move": "rock",
      "player1_rt": 539,
      "player2_rt": 0,
      "player1_outcome": "loss",
      "player2_outcome": "win",
      "player1_outcome_viewtime": 842,
      "player2_outcome_viewtime": 0,
      "player1_points": -1,
      "player2_points": 3,
      "player1_total": 45,
      "player2_total": 17
    },
    {
      "game_id": "14aad394-7f03-48a0-8599-e12fa82e3480",
      "version": "2",
      "round_index": 50,
      "player1_id": "aaafd4bd-0d3f-402e-9cd7-7ee17c483089",
      "player2_id": "bot",
      "round_begin_ts": 1583285619631,
      "player1_move": "paper",
      "player2_move": "paper",
      "player1_rt": 589,
      "player2_rt": 0,
      "player1_outcome": "tie",
      "player2_outcome": "tie",
      "player1_outcome_viewtime": 680,
      "player2_outcome_viewtime": 0,
      "player1_points": 0,
      "player2_points": 0,
      "player1_total": 44,
      "player2_total": 20
    },
    {
      "game_id": "14aad394-7f03-48a0-8599-e12fa82e3480",
      "version": "2",
      "round_index": 51,
      "player1_id": "aaafd4bd-0d3f-402e-9cd7-7ee17c483089",
      "player2_id": "bot",
      "round_begin_ts": 1583285620932,
      "player1_move": "paper",
      "player2_move": "paper",
      "player1_rt": 542,
      "player2_rt": 0,
      "player1_outcome": "tie",
      "player2_outcome": "tie",
      "player1_outcome_viewtime": 827,
      "player2_outcome_viewtime": 0,
      "player1_points": 0,
      "player2_points": 0,
      "player1_total": 44,
      "player2_total": 20
    },
    {
      "game_id": "14aad394-7f03-48a0-8599-e12fa82e3480",
      "version": "2",
      "round_index": 52,
      "player1_id": "aaafd4bd-0d3f-402e-9cd7-7ee17c483089",
      "player2_id": "bot",
      "round_begin_ts": 1583285622332,
      "player1_move": "paper",
      "player2_move": "paper",
      "player1_rt": 682,
      "player2_rt": 0,
      "player1_outcome": "tie",
      "player2_outcome": "tie",
      "player1_outcome_viewtime": 1120,
      "player2_outcome_viewtime": 0,
      "player1_points": 0,
      "player2_points": 0,
      "player1_total": 44,
      "player2_total": 20
    },
    {
      "game_id": "14aad394-7f03-48a0-8599-e12fa82e3480",
      "version": "2",
      "round_index": 53,
      "player1_id": "aaafd4bd-0d3f-402e-9cd7-7ee17c483089",
      "player2_id": "bot",
      "round_begin_ts": 1583285624162,
      "player1_move": "scissors",
      "player2_move": "paper",
      "player1_rt": 809,
      "player2_rt": 0,
      "player1_outcome": "win",
      "player2_outcome": "loss",
      "player1_outcome_viewtime": 916,
      "player2_outcome_viewtime": 0,
      "player1_points": 3,
      "player2_points": -1,
      "player1_total": 44,
      "player2_total": 20
    },
    {
      "game_id": "14aad394-7f03-48a0-8599-e12fa82e3480",
      "version": "2",
      "round_index": 54,
      "player1_id": "aaafd4bd-0d3f-402e-9cd7-7ee17c483089",
      "player2_id": "bot",
      "round_begin_ts": 1583285625923,
      "player1_move": "paper",
      "player2_move": "rock",
      "player1_rt": 496,
      "player2_rt": 0,
      "player1_outcome": "win",
      "player2_outcome": "loss",
      "player1_outcome_viewtime": 987,
      "player2_outcome_viewtime": 0,
      "player1_points": 3,
      "player2_points": -1,
      "player1_total": 47,
      "player2_total": 19
    },
    {
      "game_id": "14aad394-7f03-48a0-8599-e12fa82e3480",
      "version": "2",
      "round_index": 55,
      "player1_id": "aaafd4bd-0d3f-402e-9cd7-7ee17c483089",
      "player2_id": "bot",
      "round_begin_ts": 1583285627435,
      "player1_move": "paper",
      "player2_move": "rock",
      "player1_rt": 667,
      "player2_rt": 0,
      "player1_outcome": "win",
      "player2_outcome": "loss",
      "player1_outcome_viewtime": 731,
      "player2_outcome_viewtime": 0,
      "player1_points": 3,
      "player2_points": -1,
      "player1_total": 50,
      "player2_total": 18
    },
    {
      "game_id": "14aad394-7f03-48a0-8599-e12fa82e3480",
      "version": "2",
      "round_index": 56,
      "player1_id": "aaafd4bd-0d3f-402e-9cd7-7ee17c483089",
      "player2_id": "bot",
      "round_begin_ts": 1583285628866,
      "player1_move": "paper",
      "player2_move": "scissors",
      "player1_rt": 731,
      "player2_rt": 0,
      "player1_outcome": "loss",
      "player2_outcome": "win",
      "player1_outcome_viewtime": 923,
      "player2_outcome_viewtime": 0,
      "player1_points": -1,
      "player2_points": 3,
      "player1_total": 53,
      "player2_total": 17
    },
    {
      "game_id": "14aad394-7f03-48a0-8599-e12fa82e3480",
      "version": "2",
      "round_index": 57,
      "player1_id": "aaafd4bd-0d3f-402e-9cd7-7ee17c483089",
      "player2_id": "bot",
      "round_begin_ts": 1583285630548,
      "player1_move": "scissors",
      "player2_move": "rock",
      "player1_rt": 568,
      "player2_rt": 0,
      "player1_outcome": "loss",
      "player2_outcome": "win",
      "player1_outcome_viewtime": 1491,
      "player2_outcome_viewtime": 0,
      "player1_points": -1,
      "player2_points": 3,
      "player1_total": 52,
      "player2_total": 20
    },
    {
      "game_id": "14aad394-7f03-48a0-8599-e12fa82e3480",
      "version": "2",
      "round_index": 58,
      "player1_id": "aaafd4bd-0d3f-402e-9cd7-7ee17c483089",
      "player2_id": "bot",
      "round_begin_ts": 1583285632637,
      "player1_move": "paper",
      "player2_move": "paper",
      "player1_rt": 682,
      "player2_rt": 0,
      "player1_outcome": "tie",
      "player2_outcome": "tie",
      "player1_outcome_viewtime": 910,
      "player2_outcome_viewtime": 0,
      "player1_points": 0,
      "player2_points": 0,
      "player1_total": 51,
      "player2_total": 23
    },
    {
      "game_id": "14aad394-7f03-48a0-8599-e12fa82e3480",
      "version": "2",
      "round_index": 59,
      "player1_id": "aaafd4bd-0d3f-402e-9cd7-7ee17c483089",
      "player2_id": "bot",
      "round_begin_ts": 1583285634259,
      "player1_move": "scissors",
      "player2_move": "paper",
      "player1_rt": 627,
      "player2_rt": 0,
      "player1_outcome": "win",
      "player2_outcome": "loss",
      "player1_outcome_viewtime": 676,
      "player2_outcome_viewtime": 0,
      "player1_points": 3,
      "player2_points": -1,
      "player1_total": 51,
      "player2_total": 23
    },
    {
      "game_id": "14aad394-7f03-48a0-8599-e12fa82e3480",
      "version": "2",
      "round_index": 60,
      "player1_id": "aaafd4bd-0d3f-402e-9cd7-7ee17c483089",
      "player2_id": "bot",
      "round_begin_ts": 1583285635592,
      "player1_move": "scissors",
      "player2_move": "rock",
      "player1_rt": 678,
      "player2_rt": 0,
      "player1_outcome": "loss",
      "player2_outcome": "win",
      "player1_outcome_viewtime": 995,
      "player2_outcome_viewtime": 0,
      "player1_points": -1,
      "player2_points": 3,
      "player1_total": 54,
      "player2_total": 22
    },
    {
      "game_id": "14aad394-7f03-48a0-8599-e12fa82e3480",
      "version": "2",
      "round_index": 61,
      "player1_id": "aaafd4bd-0d3f-402e-9cd7-7ee17c483089",
      "player2_id": "bot",
      "round_begin_ts": 1583285637293,
      "player1_move": "paper",
      "player2_move": "paper",
      "player1_rt": 706,
      "player2_rt": 0,
      "player1_outcome": "tie",
      "player2_outcome": "tie",
      "player1_outcome_viewtime": 812,
      "player2_outcome_viewtime": 0,
      "player1_points": 0,
      "player2_points": 0,
      "player1_total": 53,
      "player2_total": 25
    },
    {
      "game_id": "14aad394-7f03-48a0-8599-e12fa82e3480",
      "version": "2",
      "round_index": 62,
      "player1_id": "aaafd4bd-0d3f-402e-9cd7-7ee17c483089",
      "player2_id": "bot",
      "round_begin_ts": 1583285638843,
      "player1_move": "paper",
      "player2_move": "paper",
      "player1_rt": 668,
      "player2_rt": 0,
      "player1_outcome": "tie",
      "player2_outcome": "tie",
      "player1_outcome_viewtime": 1770,
      "player2_outcome_viewtime": 0,
      "player1_points": 0,
      "player2_points": 0,
      "player1_total": 53,
      "player2_total": 25
    },
    {
      "game_id": "14aad394-7f03-48a0-8599-e12fa82e3480",
      "version": "2",
      "round_index": 63,
      "player1_id": "aaafd4bd-0d3f-402e-9cd7-7ee17c483089",
      "player2_id": "bot",
      "round_begin_ts": 1583285641312,
      "player1_move": "scissors",
      "player2_move": "paper",
      "player1_rt": 540,
      "player2_rt": 0,
      "player1_outcome": "win",
      "player2_outcome": "loss",
      "player1_outcome_viewtime": 1107,
      "player2_outcome_viewtime": 0,
      "player1_points": 3,
      "player2_points": -1,
      "player1_total": 53,
      "player2_total": 25
    },
    {
      "game_id": "14aad394-7f03-48a0-8599-e12fa82e3480",
      "version": "2",
      "round_index": 64,
      "player1_id": "aaafd4bd-0d3f-402e-9cd7-7ee17c483089",
      "player2_id": "bot",
      "round_begin_ts": 1583285642990,
      "player1_move": "scissors",
      "player2_move": "rock",
      "player1_rt": 547,
      "player2_rt": 0,
      "player1_outcome": "loss",
      "player2_outcome": "win",
      "player1_outcome_viewtime": 1005,
      "player2_outcome_viewtime": 0,
      "player1_points": -1,
      "player2_points": 3,
      "player1_total": 56,
      "player2_total": 24
    },
    {
      "game_id": "14aad394-7f03-48a0-8599-e12fa82e3480",
      "version": "2",
      "round_index": 65,
      "player1_id": "aaafd4bd-0d3f-402e-9cd7-7ee17c483089",
      "player2_id": "bot",
      "round_begin_ts": 1583285644569,
      "player1_move": "scissors",
      "player2_move": "paper",
      "player1_rt": 651,
      "player2_rt": 0,
      "player1_outcome": "win",
      "player2_outcome": "loss",
      "player1_outcome_viewtime": 649,
      "player2_outcome_viewtime": 0,
      "player1_points": 3,
      "player2_points": -1,
      "player1_total": 55,
      "player2_total": 27
    },
    {
      "game_id": "14aad394-7f03-48a0-8599-e12fa82e3480",
      "version": "2",
      "round_index": 66,
      "player1_id": "aaafd4bd-0d3f-402e-9cd7-7ee17c483089",
      "player2_id": "bot",
      "round_begin_ts": 1583285645897,
      "player1_move": "paper",
      "player2_move": "rock",
      "player1_rt": 523,
      "player2_rt": 0,
      "player1_outcome": "win",
      "player2_outcome": "loss",
      "player1_outcome_viewtime": 794,
      "player2_outcome_viewtime": 0,
      "player1_points": 3,
      "player2_points": -1,
      "player1_total": 58,
      "player2_total": 26
    },
    {
      "game_id": "14aad394-7f03-48a0-8599-e12fa82e3480",
      "version": "2",
      "round_index": 67,
      "player1_id": "aaafd4bd-0d3f-402e-9cd7-7ee17c483089",
      "player2_id": "bot",
      "round_begin_ts": 1583285647245,
      "player1_move": "paper",
      "player2_move": "scissors",
      "player1_rt": 516,
      "player2_rt": 0,
      "player1_outcome": "loss",
      "player2_outcome": "win",
      "player1_outcome_viewtime": 723,
      "player2_outcome_viewtime": 0,
      "player1_points": -1,
      "player2_points": 3,
      "player1_total": 61,
      "player2_total": 25
    },
    {
      "game_id": "14aad394-7f03-48a0-8599-e12fa82e3480",
      "version": "2",
      "round_index": 68,
      "player1_id": "aaafd4bd-0d3f-402e-9cd7-7ee17c483089",
      "player2_id": "bot",
      "round_begin_ts": 1583285648512,
      "player1_move": "rock",
      "player2_move": "scissors",
      "player1_rt": 622,
      "player2_rt": 0,
      "player1_outcome": "win",
      "player2_outcome": "loss",
      "player1_outcome_viewtime": 813,
      "player2_outcome_viewtime": 0,
      "player1_points": 3,
      "player2_points": -1,
      "player1_total": 60,
      "player2_total": 28
    },
    {
      "game_id": "14aad394-7f03-48a0-8599-e12fa82e3480",
      "version": "2",
      "round_index": 69,
      "player1_id": "aaafd4bd-0d3f-402e-9cd7-7ee17c483089",
      "player2_id": "bot",
      "round_begin_ts": 1583285649983,
      "player1_move": "scissors",
      "player2_move": "scissors",
      "player1_rt": 538,
      "player2_rt": 0,
      "player1_outcome": "tie",
      "player2_outcome": "tie",
      "player1_outcome_viewtime": 762,
      "player2_outcome_viewtime": 0,
      "player1_points": 0,
      "player2_points": 0,
      "player1_total": 63,
      "player2_total": 27
    },
    {
      "game_id": "14aad394-7f03-48a0-8599-e12fa82e3480",
      "version": "2",
      "round_index": 70,
      "player1_id": "aaafd4bd-0d3f-402e-9cd7-7ee17c483089",
      "player2_id": "bot",
      "round_begin_ts": 1583285651311,
      "player1_move": "paper",
      "player2_move": "scissors",
      "player1_rt": 584,
      "player2_rt": 0,
      "player1_outcome": "loss",
      "player2_outcome": "win",
      "player1_outcome_viewtime": 1011,
      "player2_outcome_viewtime": 0,
      "player1_points": -1,
      "player2_points": 3,
      "player1_total": 63,
      "player2_total": 27
    },
    {
      "game_id": "14aad394-7f03-48a0-8599-e12fa82e3480",
      "version": "2",
      "round_index": 71,
      "player1_id": "aaafd4bd-0d3f-402e-9cd7-7ee17c483089",
      "player2_id": "bot",
      "round_begin_ts": 1583285652938,
      "player1_move": "rock",
      "player2_move": "rock",
      "player1_rt": 567,
      "player2_rt": 0,
      "player1_outcome": "tie",
      "player2_outcome": "tie",
      "player1_outcome_viewtime": 1264,
      "player2_outcome_viewtime": 0,
      "player1_points": 0,
      "player2_points": 0,
      "player1_total": 62,
      "player2_total": 30
    },
    {
      "game_id": "14aad394-7f03-48a0-8599-e12fa82e3480",
      "version": "2",
      "round_index": 72,
      "player1_id": "aaafd4bd-0d3f-402e-9cd7-7ee17c483089",
      "player2_id": "bot",
      "round_begin_ts": 1583285654797,
      "player1_move": "rock",
      "player2_move": "rock",
      "player1_rt": 989,
      "player2_rt": 0,
      "player1_outcome": "tie",
      "player2_outcome": "tie",
      "player1_outcome_viewtime": 883,
      "player2_outcome_viewtime": 0,
      "player1_points": 0,
      "player2_points": 0,
      "player1_total": 62,
      "player2_total": 30
    },
    {
      "game_id": "14aad394-7f03-48a0-8599-e12fa82e3480",
      "version": "2",
      "round_index": 73,
      "player1_id": "aaafd4bd-0d3f-402e-9cd7-7ee17c483089",
      "player2_id": "bot",
      "round_begin_ts": 1583285656718,
      "player1_move": "paper",
      "player2_move": "rock",
      "player1_rt": 1017,
      "player2_rt": 0,
      "player1_outcome": "win",
      "player2_outcome": "loss",
      "player1_outcome_viewtime": 1013,
      "player2_outcome_viewtime": 0,
      "player1_points": 3,
      "player2_points": -1,
      "player1_total": 62,
      "player2_total": 30
    }
  ],
  "player2_botid": "ab9dd9b6-1574-4fcb-93ab-9bdaf6e1ff74",
  "player2_bot_strategy": "win_positive_lose_negative",
  "player2_bot_move_probabilities": {
    "win": {
      "rock": {
        "rock": 0.04999999999999999,
        "paper": 0.9,
        "scissors": 0.04999999999999999
      },
      "paper": {
        "rock": 0.04999999999999999,
        "paper": 0.04999999999999999,
        "scissors": 0.9
      },
      "scissors": {
        "rock": 0.9,
        "paper": 0.04999999999999999,
        "scissors": 0.04999999999999999
      }
    },
    "loss": {
      "rock": {
        "rock": 0.04999999999999999,
        "paper": 0.04999999999999999,
        "scissors": 0.9
      },
      "paper": {
        "rock": 0.9,
        "paper": 0.04999999999999999,
        "scissors": 0.04999999999999999
      },
      "scissors": {
        "rock": 0.04999999999999999,
        "paper": 0.9,
        "scissors": 0.04999999999999999
      }
    },
    "tie": {
      "rock": {
        "rock": 0.9,
        "paper": 0.04999999999999999,
        "scissors": 0.04999999999999999
      },
      "paper": {
        "rock": 0.04999999999999999,
        "paper": 0.9,
        "scissors": 0.04999999999999999
      },
      "scissors": {
        "rock": 0.04999999999999999,
        "paper": 0.04999999999999999,
        "scissors": 0.9
      }
    }
  }
}